ai_terminal/MistralTerminal.py
ai_terminal/__init__.py
ai_terminal-0.1.0rc1.dist-info/LICENSE
ai_terminal-0.1.0rc1.dist-info/METADATA
ai_terminal-0.1.0rc1.dist-info/WHEEL
ai_terminal-0.1.0rc1.dist-info/entry_points.txt
ai_terminal-0.1.0rc1.dist-info/top_level.txt
ai_terminal-0.1.0rc1.dist-info/RECORD
