Metadata-Version: 2.1
Name: ai-terminal
Version: 0.1.0rc1
Summary: Interface to interact with a chatbot in Linux terminal
Home-page: 
Author-email: vladislav.yastrebov@minesparis.psl.eu
License: BSD-3-Clause license
Classifier: Development Status :: 4 - Beta
Classifier: Topic :: Scientific/Engineering
License-File: LICENSE
Requires-Dist: mistralai
Requires-Dist: prompt-toolkit
